<?xml version="1.0" encoding="UTF-8"?>
<objects serializationModel="Studio.02.00.00">
	<object class="AudioFile" id="{0397a486-e788-4886-8420-6450f69499ec}">
		<property name="assetPath">
			<value>car-outside.wav</value>
		</property>
		<property name="frequencyInKHz">
			<value>44.0999985</value>
		</property>
		<property name="channelCount">
			<value>2</value>
		</property>
		<property name="length">
			<value>4.800566893424036</value>
		</property>
		<relationship name="masterAssetFolder">
			<destination>{cd95300f-5517-4993-bb62-db94ba49f3b3}</destination>
		</relationship>
	</object>
</objects>
